setup.py
autosync/__init__.py
autosync/daemon.py
autosync/files.py
autosync.egg-info/PKG-INFO
autosync.egg-info/SOURCES.txt
autosync.egg-info/dependency_links.txt
autosync.egg-info/requires.txt
autosync.egg-info/top_level.txt
autosync.egg-info/zip-safe
autosync/actors/__init__.py
autosync/actors/s3.py
scripts/autosync