Metadata-Version: 1.0
Name: autosync
Version: 0.0.4
Summary: Efficent synchronization of the local file system to S3
Home-page: https://github.com/wnyc/autosync
Author: Adam DePrince
Author-email: adeprince@nypublicradio.org
License: GPL
Platform: UNKNOWN
